nature/__init__.py
nature/analysis.py
nature/chromosome.py
nature/codon.py
nature/codons/__init__.py
nature/codons/primitives.py
nature/codons/series.py
nature/color.py
nature/db/__init__.py
nature/db/base.py
nature/db/models.py
nature/db/pickle_entity.py
nature/db/session.py
nature/db/utils.py
nature/evaluator.py
nature/hof.py
nature/incubators/__init__.py
nature/incubators/early_termination.py
nature/incubators/incubator.py
nature/incubators/pipe.py
nature/incubators/population_sizing.py
nature/incubators/shared_memory.py
nature/incubators/workers/__init__.py
nature/incubators/workers/base_worker.py
nature/logging.py
nature/nsga.py
nature/random.py
nature/ring_buffer.py
nature/scikit_helpers.py
nature/selection.py
nature/species.py
nature/tree.py
nature/typing.py
nature/utils.py
python_nature-1.1.0.dist-info/LICENSE
python_nature-1.1.0.dist-info/METADATA
python_nature-1.1.0.dist-info/WHEEL
python_nature-1.1.0.dist-info/RECORD
