Metadata-Version: 2.3
Name: python-nature
Version: 1.1.0
Summary: Strongly-typed genetic programming for evolving instance methods on vanilla Python classes
License: MIT
Keywords: genetic-programming,genetic-algorithms,symbolic-regression,optimization,evolutionary-computation,multi-objective-optimization,nsga2,nsga3,machine-learning,metaheuristics
Author: dg
Author-email: dgabriele@users.noreply.github.com
Requires-Python: >=3.13,<3.14
Classifier: Development Status :: 4 - Beta
Classifier: Intended Audience :: Developers
Classifier: Intended Audience :: Science/Research
Classifier: License :: OSI Approved :: MIT License
Classifier: Operating System :: OS Independent
Classifier: Programming Language :: Python :: 3
Classifier: Programming Language :: Python :: 3.13
Classifier: Topic :: Scientific/Engineering :: Artificial Intelligence
Classifier: Topic :: Scientific/Engineering :: Mathematics
Classifier: Topic :: Software Development :: Libraries :: Python Modules
Classifier: Typing :: Typed
Provides-Extra: database
Requires-Dist: asyncpg (>=0.30.0,<0.31.0) ; extra == "database"
Requires-Dist: attrs (>=25.3.0,<26.0.0)
Requires-Dist: cachetools (>=6.1.0,<7.0.0)
Requires-Dist: filterpy (>=1.4.5,<2.0.0)
Requires-Dist: graphviz (>=0.20.3,<0.21.0)
Requires-Dist: loguru (>=0.7.3,<0.8.0)
Requires-Dist: matplotlib (>=3.10.1,<4.0.0)
Requires-Dist: memoized-property (>=1.0.3,<2.0.0)
Requires-Dist: numba (>=0.61.0,<0.62.0)
Requires-Dist: numpy (>=2.2.3,<3.0.0)
Requires-Dist: numpy-ringbuffer (>=0.2.2,<0.3.0)
Requires-Dist: pandas (>=2.2.3,<3.0.0)
Requires-Dist: psycopg2 (>=2.9.10,<3.0.0) ; extra == "database"
Requires-Dist: pykalman (>=0.10.1,<0.11.0)
Requires-Dist: pymoo (>=0.6.1,<0.7.0)
Requires-Dist: pywavelets (>=1.8.0,<2.0.0)
Requires-Dist: scikit-learn (>=1.6.1,<2.0.0)
Requires-Dist: scipy (>=1.15.2,<2.0.0)
Requires-Dist: sqlalchemy (>=2.0.41,<3.0.0) ; extra == "database"
Requires-Dist: statsmodels (>=0.14.4,<0.15.0)
Requires-Dist: tabulate (>=0.9.0,<0.10.0)
Project-URL: Documentation, https://github.com/dgabriele/nature#readme
Project-URL: Homepage, https://github.com/dgabriele/nature
Project-URL: Repository, https://github.com/dgabriele/nature
